{
  "meta": {
    "capturedAt": "2026-04-25T08:28:52.145Z",
    "sourceFiles": {
      "public": "/home/runner/work/vortex-content/vortex-content/content/public-human-comments.json",
      "review": "/home/runner/work/vortex-content/vortex-content/content/place-review-snippets.json",
      "forum": "/home/runner/work/vortex-content/vortex-content/content/forum-snippets.json",
      "signals": "/home/runner/work/vortex-content/vortex-content/content/city-signals.json",
      "news": "/home/runner/work/vortex-content/vortex-content/content/news-snippets.json",
      "social": "/home/runner/work/vortex-content/vortex-content/content/social-snippets.json",
      "world": "/home/runner/work/vortex-content/vortex-content/content/world-trends.json",
      "nightlife": "/home/runner/work/vortex-content/vortex-content/content/ra-berlin-events.json",
      "trends": "/home/runner/work/vortex-content/vortex-content/content/google-trends.json",
      "transport": "/home/runner/work/vortex-content/vortex-content/content/transport-signals.json",
      "weather": "/home/runner/work/vortex-content/vortex-content/content/weather-signals.json",
      "sports": "/home/runner/work/vortex-content/vortex-content/content/sports-signals.json"
    },
    "totalItems": 337
  },
  "rows": [
    {
      "city_id": "london",
      "captured_at": "2026-04-25T08:28:52.145Z",
      "mood_score": 0.472,
      "mood_label": "mixed",
      "mood_summary": "The city feels mixed. Right now the pressure is mostly around general, transit, money. The signal still feels live today.",
      "dominant_sentiment": "neutral",
      "source_counts": {
        "public": 5,
        "review": 2,
        "forum": 4,
        "signals": 1,
        "news": 25,
        "social": 2,
        "world": 5,
        "trends": 8,
        "transport": 5,
        "weather": 1
      },
      "languages": [
        "en"
      ],
      "drivers": [
        {
          "source_family": "social",
          "source_origin": "x_post",
          "language": "en",
          "valence": -0.575,
          "recency_weight": 1.04,
          "excerpt": "victoria line delay hit at the exact point in the morning where everyone has already decided not to be dramatic about it"
        },
        {
          "source_family": "transport",
          "source_origin": "tfl",
          "language": "en",
          "valence": -0.575,
          "recency_weight": 1.08,
          "excerpt": "London transit Piccadilly: Part Closure PICCADILLY LINE: Saturday 25 and Sunday 26 April, no service between Rayners Lane and Uxbridge. Use METROPOLITAN LINE se"
        },
        {
          "source_family": "transport",
          "source_origin": "tfl",
          "language": "en",
          "valence": -0.575,
          "recency_weight": 1.08,
          "excerpt": "London transit Piccadilly: Part Closure PICCADILLY LINE: Saturday 25 April, from 0530, and all day Sunday 26 April, no service between Wood Green and Cockfoster"
        },
        {
          "source_family": "transport",
          "source_origin": "tfl",
          "language": "en",
          "valence": -0.575,
          "recency_weight": 1.08,
          "excerpt": "London transit Waterloo & City: Planned Closure Waterloo & City line: service operates 06:00 until 00:30, Monday to Friday only. There is no service on Saturdays, Sunda"
        },
        {
          "source_family": "news",
          "source_origin": "google_news_rss",
          "language": "en",
          "valence": -0.575,
          "recency_weight": 1.08,
          "excerpt": "Which Tube lines are running as second 24-hour strike hits London? - London Evening Standard. Which Tube lines are running as second 24-hour strike hits London?"
        }
      ],
      "metadata": {
        "source_item_count": 58,
        "average_valence": -0.084,
        "dominant_themes": [
          "general",
          "transit",
          "money"
        ],
        "freshness_score": 0.915
      }
    },
    {
      "city_id": "berlin",
      "captured_at": "2026-04-25T08:28:52.145Z",
      "mood_score": 0.484,
      "mood_label": "mixed",
      "mood_summary": "The city feels mixed. Right now the pressure is mostly around general, routine, transit. The signal is very current.",
      "dominant_sentiment": "neutral",
      "source_counts": {
        "public": 1,
        "review": 2,
        "forum": 4,
        "signals": 1,
        "news": 25,
        "social": 2,
        "world": 5,
        "nightlife": 40,
        "trends": 8,
        "weather": 1
      },
      "languages": [
        "de",
        "en"
      ],
      "drivers": [
        {
          "source_family": "social",
          "source_origin": "x_post",
          "language": "de",
          "valence": -1,
          "recency_weight": 1.04,
          "excerpt": "ringbahn wieder chaos und trotzdem stehen alle da als wäre das nur eine weitere Wetterlage. berlin macht aus allem ein Klima"
        },
        {
          "source_family": "forum",
          "source_origin": "local_forum",
          "language": "en",
          "valence": -1,
          "recency_weight": 1.04,
          "excerpt": "When you knew you were actually living here. Neukölln. The sound of a neighbor's saxophone cutting through the morning chaos of a bus strike—classic Neukölln vibes that remind you "
        },
        {
          "source_family": "signals",
          "source_origin": "auto_city_snapshot",
          "language": "en",
          "valence": -1,
          "recency_weight": 0.72,
          "excerpt": "A thick layer of gray clouds blankets the city, hinting at rain, with a cool breeze carrying the scent of damp earth.. The U-Bahn is running smoothly again, but there's a noticeabl"
        },
        {
          "source_family": "world",
          "source_origin": "committed_world_fallback",
          "language": "en",
          "valence": -0.575,
          "recency_weight": 0.56,
          "excerpt": "The internet is tired of paying premium prices for mediocre basics. premium pricing for ordinary disappointment. the product is now just being charged twice. people are doing philo"
        },
        {
          "source_family": "world",
          "source_origin": "committed_world_fallback",
          "language": "en",
          "valence": -0.575,
          "recency_weight": 0.56,
          "excerpt": "Travel frustration is back in the global bloodstream. airport energy leaking into normal life. one more platform change and i'm becoming ideological. delays and rolling bags make h"
        }
      ],
      "metadata": {
        "source_item_count": 89,
        "average_valence": -0.046,
        "dominant_themes": [
          "general",
          "routine",
          "transit"
        ],
        "freshness_score": 0.937
      }
    },
    {
      "city_id": "sf",
      "captured_at": "2026-04-25T08:28:52.145Z",
      "mood_score": 0.446,
      "mood_label": "mixed",
      "mood_summary": "The city feels mixed. Right now the pressure is mostly around general, transit, routine. The signal still feels live today.",
      "dominant_sentiment": "neutral",
      "source_counts": {
        "public": 5,
        "review": 2,
        "forum": 4,
        "signals": 1,
        "news": 25,
        "social": 2,
        "world": 5,
        "trends": 8,
        "weather": 1
      },
      "languages": [
        "en"
      ],
      "drivers": [
        {
          "source_family": "review",
          "source_origin": "maps_review",
          "language": "en",
          "valence": 0.5,
          "recency_weight": 1.04,
          "excerpt": "taqueria. Mission. The line looks like a small housing crisis but moves fast. Best move is to go when the fog is still deciding what kind of day it is."
        },
        {
          "source_family": "news",
          "source_origin": "google_news_rss",
          "language": "en",
          "valence": -0.575,
          "recency_weight": 0.56,
          "excerpt": "BART equipment problem causes major delays system wide - CBS News. BART equipment problem causes major delays system wide"
        },
        {
          "source_family": "news",
          "source_origin": "google_news_rss",
          "language": "en",
          "valence": -0.575,
          "recency_weight": 0.56,
          "excerpt": "Dozens of S.F. tenants stunned by eviction notices despite paying rent - San Francisco Chronicle. Dozens of S.F. tenants stunned by eviction notices despite paying rent"
        },
        {
          "source_family": "signals",
          "source_origin": "auto_city_snapshot",
          "language": "en",
          "valence": -0.575,
          "recency_weight": 0.72,
          "excerpt": "Gray clouds hover over the city, thick with the promise of rain but holding back, casting a muted light over the bustling streets.. The BART stations are unusually chaotic, with co"
        },
        {
          "source_family": "world",
          "source_origin": "committed_world_fallback",
          "language": "en",
          "valence": -0.075,
          "recency_weight": 0.56,
          "excerpt": "The internet is tired of paying premium prices for mediocre basics. premium pricing for ordinary disappointment. the product is now just being charged twice. there is a very local "
        }
      ],
      "metadata": {
        "source_item_count": 53,
        "average_valence": -0.012,
        "dominant_themes": [
          "general",
          "transit",
          "routine"
        ],
        "freshness_score": 0.825
      }
    },
    {
      "city_id": "barcelona",
      "captured_at": "2026-04-25T08:28:52.145Z",
      "mood_score": 0.491,
      "mood_label": "mixed",
      "mood_summary": "The city feels mixed. Right now the pressure is mostly around general, transit, tourism.",
      "dominant_sentiment": "neutral",
      "source_counts": {
        "review": 2,
        "forum": 4,
        "signals": 1,
        "news": 25,
        "social": 91,
        "world": 5,
        "trends": 8,
        "weather": 1
      },
      "languages": [
        "ca",
        "en",
        "es",
        "ru"
      ],
      "drivers": [
        {
          "source_family": "social",
          "source_origin": "x_post",
          "language": "es",
          "valence": -0.575,
          "recency_weight": 1.04,
          "excerpt": "otra mañana escuchando maletas por el Raval como si el barrio tuviera check-in. luego te dicen que exageras con el tema turístico"
        },
        {
          "source_family": "world",
          "source_origin": "committed_world_fallback",
          "language": "en",
          "valence": -1,
          "recency_weight": 0.56,
          "excerpt": "The internet is tired of paying premium prices for mediocre basics. premium pricing for ordinary disappointment. the product is now just being charged twice. locals and expats are "
        },
        {
          "source_family": "signals",
          "source_origin": "auto_city_snapshot",
          "language": "en",
          "valence": -1,
          "recency_weight": 0.72,
          "excerpt": "The sky is a patchwork of gray clouds, punctuated by brief bursts of golden sunlight that dance on the streets of the Eixample.. Commuters are restless at the Sants station, freque"
        },
        {
          "source_family": "social",
          "source_origin": "telegram_group",
          "language": "ru",
          "valence": -0.575,
          "recency_weight": 0.56,
          "excerpt": "Везде просили за 3 месяца, но именно пэйслипы) В банках и арендодатели. Нравится им эта бумажка уж очень"
        },
        {
          "source_family": "social",
          "source_origin": "telegram_group",
          "language": "ru",
          "valence": -0.575,
          "recency_weight": 0.56,
          "excerpt": "Забудьте про испанский документ) Просто загуглите \"пэйслип\", это довольно простая бумага. Ни один арендодатель не жаловался, а прошли мы через многих"
        }
      ],
      "metadata": {
        "source_item_count": 137,
        "average_valence": -0.027,
        "dominant_themes": [
          "general",
          "transit",
          "tourism"
        ],
        "freshness_score": 0.636
      }
    }
  ]
}
