[
  {
    "cityId": "barcelona",
    "name": "Sabes una Cosa",
    "neighborhood": "Barcelona",
    "category": "restaurant",
    "rating": null,
    "lat": 41.4019328,
    "lng": 2.162054,
    "fact": "mexican, hours: Mo-Fr 20:00-23:30; Sa 13:30-15:30,20:00-23:30, outdoor seating, has website",
    "source": "openstreetmap"
  },
  {
    "cityId": "barcelona",
    "name": "Aladdin",
    "neighborhood": "",
    "category": "restaurant",
    "rating": null,
    "lat": 41.4086056,
    "lng": 2.1745607,
    "fact": "wheelchair accessible",
    "source": "openstreetmap"
  },
  {
    "cityId": "barcelona",
    "name": "La Poma",
    "neighborhood": "Barcelona",
    "category": "restaurant",
    "rating": null,
    "lat": 41.3843881,
    "lng": 2.170482,
    "fact": "italian, wheelchair accessible",
    "source": "openstreetmap"
  },
  {
    "cityId": "barcelona",
    "name": "Vila Viniteca",
    "neighborhood": "",
    "category": "restaurant",
    "rating": null,
    "lat": 41.3824742,
    "lng": 2.1815472,
    "fact": "hours: Mo-Sa 08:30-20:30, has website",
    "source": "openstreetmap"
  },
  {
    "cityId": "barcelona",
    "name": "La Fourmi",
    "neighborhood": "",
    "category": "bar",
    "rating": null,
    "lat": 41.4019257,
    "lng": 2.1616543,
    "fact": "wheelchair accessible",
    "source": "openstreetmap"
  },
  {
    "cityId": "barcelona",
    "name": "Rambla Poblenou",
    "neighborhood": "",
    "category": "cafe",
    "rating": null,
    "lat": 41.4046882,
    "lng": 2.1967694,
    "fact": "spanish",
    "source": "openstreetmap"
  },
  {
    "cityId": "barcelona",
    "name": "Babilonia",
    "neighborhood": "",
    "category": "restaurant",
    "rating": null,
    "lat": 41.4050316,
    "lng": 2.1742781,
    "fact": "",
    "source": "openstreetmap"
  },
  {
    "cityId": "barcelona",
    "name": "Restaurant Buffet",
    "neighborhood": "",
    "category": "restaurant",
    "rating": null,
    "lat": 41.3742363,
    "lng": 2.1522045,
    "fact": "",
    "source": "openstreetmap"
  },
  {
    "cityId": "barcelona",
    "name": "Restaurante UN-ZA",
    "neighborhood": "",
    "category": "restaurant",
    "rating": null,
    "lat": 41.40537,
    "lng": 2.1934837,
    "fact": "japanese, hours: Mo-Su 13:00-16:00,20:00-23:30",
    "source": "openstreetmap"
  },
  {
    "cityId": "barcelona",
    "name": "Bello Italy",
    "neighborhood": "",
    "category": "restaurant",
    "rating": null,
    "lat": 41.3812444,
    "lng": 2.1728937,
    "fact": "",
    "source": "openstreetmap"
  },
  {
    "cityId": "barcelona",
    "name": "Central Rambla",
    "neighborhood": "",
    "category": "restaurant",
    "rating": null,
    "lat": 41.3782716,
    "lng": 2.1761732,
    "fact": "outdoor seating",
    "source": "openstreetmap"
  },
  {
    "cityId": "barcelona",
    "name": "Zim",
    "neighborhood": "",
    "category": "bar",
    "rating": null,
    "lat": 41.3830486,
    "lng": 2.178292,
    "fact": "hours: Mo-Su 18:00-23:00",
    "source": "openstreetmap"
  },
  {
    "cityId": "barcelona",
    "name": "cent111onze",
    "neighborhood": "",
    "category": "restaurant",
    "rating": null,
    "lat": 41.383726,
    "lng": 2.1709656,
    "fact": "wheelchair accessible",
    "source": "openstreetmap"
  },
  {
    "cityId": "barcelona",
    "name": "Cèntric",
    "neighborhood": "",
    "category": "cafe",
    "rating": null,
    "lat": 41.3847302,
    "lng": 2.1680967,
    "fact": "",
    "source": "openstreetmap"
  },
  {
    "cityId": "barcelona",
    "name": "Palacio de China",
    "neighborhood": "",
    "category": "restaurant",
    "rating": null,
    "lat": 41.3934539,
    "lng": 2.1881434,
    "fact": "chinese",
    "source": "openstreetmap"
  },
  {
    "cityId": "berlin",
    "name": "Dokumentationszentrum Flucht, Vertreibung, Versöhnung",
    "neighborhood": "Kreuzberg",
    "category": "museum",
    "rating": null,
    "lat": 52.5048708,
    "lng": 13.3822143,
    "fact": "hours: Tu-Su 10:00-19:00; Mo off, wheelchair accessible, has website",
    "source": "openstreetmap"
  },
  {
    "cityId": "berlin",
    "name": "Seequell",
    "neighborhood": "",
    "category": "pub",
    "rating": null,
    "lat": 52.5550162,
    "lng": 13.3616898,
    "fact": "hours: PH,Mo-Su 12:00-18:00+, outdoor seating, wheelchair accessible",
    "source": "openstreetmap"
  },
  {
    "cityId": "berlin",
    "name": "Maximilians",
    "neighborhood": "Mitte",
    "category": "restaurant",
    "rating": null,
    "lat": 52.5113441,
    "lng": 13.3891811,
    "fact": "bavarian, hours: Mo-Su 11:30-23:30, outdoor seating, wheelchair accessible",
    "source": "openstreetmap"
  },
  {
    "cityId": "berlin",
    "name": "Immertreu",
    "neighborhood": "Prenzlauer Berg",
    "category": "bar",
    "rating": null,
    "lat": 52.5363657,
    "lng": 13.425073,
    "fact": "hours: Mo-Sa 20:00-24:00+",
    "source": "openstreetmap"
  },
  {
    "cityId": "berlin",
    "name": "Matzbach",
    "neighborhood": "",
    "category": "restaurant",
    "rating": null,
    "lat": 52.5202106,
    "lng": 13.4118079,
    "fact": "outdoor seating",
    "source": "openstreetmap"
  },
  {
    "cityId": "berlin",
    "name": "Shezan",
    "neighborhood": "Mitte",
    "category": "restaurant",
    "rating": null,
    "lat": 52.512146,
    "lng": 13.4081288,
    "fact": "indian, hours: Mo-Su 11:30-23:30, outdoor seating",
    "source": "openstreetmap"
  },
  {
    "cityId": "berlin",
    "name": "Gedenkstätte Deutscher Widerstand",
    "neighborhood": "",
    "category": "museum",
    "rating": null,
    "lat": 52.5076051,
    "lng": 13.3629858,
    "fact": "hours: Mo-Fr 09:00-18:00; Sa-Su 10:00-18:00, has website",
    "source": "openstreetmap"
  },
  {
    "cityId": "berlin",
    "name": "Akemi",
    "neighborhood": "Prenzlauer Berg",
    "category": "restaurant",
    "rating": null,
    "lat": 52.5376526,
    "lng": 13.4212143,
    "fact": "asian, outdoor seating",
    "source": "openstreetmap"
  },
  {
    "cityId": "berlin",
    "name": "SowohlAlsAuch",
    "neighborhood": "Prenzlauer Berg",
    "category": "cafe",
    "rating": null,
    "lat": 52.5382237,
    "lng": 13.4204986,
    "fact": "german, coffee_shop, hours: Mo-Su 08:00-23:00, outdoor seating, has website",
    "source": "openstreetmap"
  },
  {
    "cityId": "berlin",
    "name": "Eiscafe Eisberg",
    "neighborhood": "Gesundbrunnen",
    "category": "cafe",
    "rating": null,
    "lat": 52.5388551,
    "lng": 13.3960965,
    "fact": "outdoor seating, wheelchair accessible, has website",
    "source": "openstreetmap"
  },
  {
    "cityId": "berlin",
    "name": "Heritage",
    "neighborhood": "Mitte",
    "category": "restaurant",
    "rating": null,
    "lat": 52.514689,
    "lng": 13.3909281,
    "fact": "hours: Mo-Su 06:30-23:00",
    "source": "openstreetmap"
  },
  {
    "cityId": "berlin",
    "name": "Kante",
    "neighborhood": "Kreuzberg",
    "category": "restaurant",
    "rating": null,
    "lat": 52.5001321,
    "lng": 13.4387908,
    "fact": "hours: Mo-Su 18:00-00:00, outdoor seating",
    "source": "openstreetmap"
  },
  {
    "cityId": "berlin",
    "name": "Zollpackhof",
    "neighborhood": "Moabit",
    "category": "restaurant",
    "rating": null,
    "lat": 52.5212821,
    "lng": 13.3668503,
    "fact": "german, hours: Mo-Su 11:00-00:00, outdoor seating, wheelchair accessible, has website",
    "source": "openstreetmap"
  },
  {
    "cityId": "berlin",
    "name": "Einstein Kaffee",
    "neighborhood": "",
    "category": "cafe",
    "rating": null,
    "lat": 52.5113571,
    "lng": 13.3894708,
    "fact": "coffee_shop, hours: Mo-Fr 07:00-20:00; PH,Sa-Su 09:00-19:00, outdoor seating, wheelchair accessible",
    "source": "openstreetmap"
  },
  {
    "cityId": "berlin",
    "name": "Mad Meals",
    "neighborhood": "Prenzlauer Berg",
    "category": "restaurant",
    "rating": null,
    "lat": 52.5406178,
    "lng": 13.414039,
    "fact": "mexican, outdoor seating",
    "source": "openstreetmap"
  }
]
